raspberrytq.py
raspberrytq-0.1.0.dist-info/METADATA
raspberrytq-0.1.0.dist-info/WHEEL
raspberrytq-0.1.0.dist-info/entry_points.txt
raspberrytq-0.1.0.dist-info/top_level.txt
raspberrytq-0.1.0.dist-info/RECORD
