Metadata-Version: 2.2
Name: raspberrytq
Version: 0.1.0
Summary: MicroPython CLI for Raspberry Pi Pico RTC and LED control.
Home-page: https://github.com/PyWebServerHosts/RaspberryTQ/
Author: Xscripts Inc.
Author-email: sunnyplaysyt9@gmaial.com
Classifier: Programming Language :: Python :: 3
Classifier: Operating System :: OS Independent
Requires-Python: >=3.6
Dynamic: author
Dynamic: author-email
Dynamic: classifier
Dynamic: home-page
Dynamic: requires-python
Dynamic: summary
